PyTypeFx/__init__.py
PyTypeFx/cli.py
PyTypeFx/colors.py
PyTypeFx/constant.py
PyTypeFx/decorator.py
PyTypeFx/effects.py
PyTypeFx/utility.py
PyTypeFx/writers.py
pytypefx-0.1.1.dist-info/licenses/LICENSE
pytypefx-0.1.1.dist-info/METADATA
pytypefx-0.1.1.dist-info/WHEEL
pytypefx-0.1.1.dist-info/entry_points.txt
pytypefx-0.1.1.dist-info/top_level.txt
pytypefx-0.1.1.dist-info/RECORD
